CHANGES.md
CHANGES.txt
CITATION.md
GETTING_STARTED.md
INSTALLATION.md
LICENSE
MANIFEST.in
README.md
README.txt
TEST.md
TODO.md
VERSION
requirements.txt
setup.cfg
setup.py
PyFBA/__init__.py
PyFBA/version.py
PyFBA.egg-info/PKG-INFO
PyFBA.egg-info/SOURCES.txt
PyFBA.egg-info/dependency_links.txt
PyFBA.egg-info/entry_points.txt
PyFBA.egg-info/requires.txt
PyFBA.egg-info/top_level.txt
PyFBA.egg-info/zip-safe
PyFBA/Biochemistry/__init__.py
PyFBA/Biochemistry/ModelSEEDDatabase/ModelSEEDLICENSE.txt
PyFBA/Biochemistry/ModelSEEDDatabase/README.md
PyFBA/Biochemistry/ModelSEEDDatabase/__init__.py
PyFBA/Biochemistry/ModelSEEDDatabase/Annotations/Complexes.tsv
PyFBA/Biochemistry/ModelSEEDDatabase/Annotations/Roles.tsv
PyFBA/Biochemistry/ModelSEEDDatabase/Annotations/__init__.py
PyFBA/Biochemistry/ModelSEEDDatabase/Biochemistry/__init__.py
PyFBA/Biochemistry/ModelSEEDDatabase/Biochemistry/compounds.json
PyFBA/Biochemistry/ModelSEEDDatabase/Biochemistry/reactions.json
PyFBA/Biochemistry/ModelSEEDDatabase/Templates/__init__.py
PyFBA/Biochemistry/ModelSEEDDatabase/Templates/Core/Reactions.tsv
PyFBA/Biochemistry/ModelSEEDDatabase/Templates/Core/__init__.py
PyFBA/Biochemistry/ModelSEEDDatabase/Templates/Fungi/Reactions.tsv
PyFBA/Biochemistry/ModelSEEDDatabase/Templates/Fungi/__init__.py
PyFBA/Biochemistry/ModelSEEDDatabase/Templates/GramNegative/Reactions.tsv
PyFBA/Biochemistry/ModelSEEDDatabase/Templates/GramNegative/__init__.py
PyFBA/Biochemistry/ModelSEEDDatabase/Templates/GramPositive/Reactions.tsv
PyFBA/Biochemistry/ModelSEEDDatabase/Templates/GramPositive/__init__.py
PyFBA/Biochemistry/ModelSEEDDatabase/Templates/Microbial/Reactions.tsv
PyFBA/Biochemistry/ModelSEEDDatabase/Templates/Microbial/__init__.py
PyFBA/Biochemistry/ModelSEEDDatabase/Templates/Mycobacteria/Reactions.tsv
PyFBA/Biochemistry/ModelSEEDDatabase/Templates/Mycobacteria/__init__.py
PyFBA/Biochemistry/SEED/__init__.py
PyFBA/Biochemistry/SEED/Subsystems/SS_functions.txt
PyFBA/Biochemistry/SEED/Subsystems/__init__.py
PyFBA/Biochemistry/media/ArgonneLB.txt
PyFBA/Biochemistry/media/MOPS_NoC_2-Deoxy-D-Ribose.txt
PyFBA/Biochemistry/media/MOPS_NoC_4-Hydroxy-Phenylacetate.txt
