Metadata-Version: 1.1
Name: PyFBA
Version: 2.62
Summary: A Python implementation of flux balance analysis
Home-page: http://linsalrob.github.io/PyFBA/
Author: Rob Edwards
Author-email: raedwards@gmail.com
License: The MIT License (MIT)
Platform: any
Classifier: Development Status :: 4 - Beta
Classifier: Intended Audience :: Science/Research
Classifier: License :: OSI Approved :: MIT License
Classifier: Natural Language :: English
Classifier: Operating System :: MacOS :: MacOS X
Classifier: Operating System :: POSIX :: Linux
Classifier: Operating System :: Unix
Classifier: Programming Language :: Python :: 2.7
Classifier: Programming Language :: Python :: 3.0
Classifier: Topic :: Scientific/Engineering :: Bio-Informatics
